pinta/cli/__init__.py
pinta/cli/__main__.py
pinta-0.0.1.dist-info/entry_points.txt
pinta-0.0.1.dist-info/LICENSE
pinta-0.0.1.dist-info/WHEEL
pinta-0.0.1.dist-info/METADATA
pinta-0.0.1.dist-info/RECORD
